Workbook

Sheet Datos
B2: Saldos ajustados del Balance de Comprobación al 31.01.2026
B3: Cuentas | C3: S/.
B4: Efectivo y equivalente de efectivo | C4: ?
B5: Costo de obra - ER | C5: 5000000 | D5: ER - negativo
B6: Valorizaciones por cobrar | C6: 2400000
B7: Inventarios de materiales de construcción | C7: 1600000
B8: Ingreso por enajenación activo | C8: 475000 | D8: Resultados - otros ingresos
B9: Gasto por impuesto a las ganancias | C9: 182000 | D9: ER - VA EN NEGATIVO, ultima deducción para hallar la utilidad neta
B10: Tributos por pagar | C10: 756000 | D10: PAS CORR
B11: Gastos financieros | C11: 18000 | D11: ER - VA EN NEGATIVO
B12: Obligaciones financieras (CP) | C12: 1620000 | D12: PASIVO CORRIENTE
B13: Gasto de administración | C13: 1300000
B14: Obligaciones financieras (LP) | C14: 4000000 | D14: PAS CORR
B15: Ingresos por valorizaciones | C15: 7000000 | D15: ESTADO DE RESULTADOS, ANTES DE UTIL. BRUTA
B16: Reserva legal | C16: 420000 | D16: PAT
B17: Resultado acumulado al 31.12.2024 | C17: 1000000 | D17: NO SIRVE EL RA ES ANUAL
B18: Maquinaria y equipo, IME, PPE | C18: 7500000 | D18: ACT NO CORR
B19: Gastos de comisiones | C19: 176000 | D19: RESULTADOS
B20: Cuentas por pagar subcontratistas | C20: 1405000 | D20: PAS CORR - CUENTAS POR PAGAR COMERCIALES
B21: Costo enajenación activo | C21: 500000 | D21: ER - DESPUÉS DE LA UTILIDAD OPERATIVA Y ANTES DE LA UTILIDAD ANTES DE IMPUESTOS
B22: Capital social | C22: =2174000-105000+90000 -> 2159000 | D22: PAT
C25: =+C23

Sheet Estructura
B1: Constructora MAGNET S.A. | G1: Constructora MAGNET S.A.
B2: Estado de Situacion Financiera | G2: Estado de Resultados
B3: Al 31 de enero de 2026 | G3: Periodo terminado el 31 de enero de 2026
B4: En soles | G4: En soles
B5: Activos | D5: Pasivo y Patrimonio | G5: =Datos!B15 -> Ingresos por valorizaciones | H5: =Datos!C15 -> 7000000 | J5: TOTAL PASIVO + PATRIMONIO = S/ 11,659,000
B6: Activo Corriente | D6: Pasivo Corriente | G6: =Datos!B5 -> Costo de obra - ER | H6: =(-Datos!C5) -> -5000000 | J6: TOTAL ACTIVOS sin efectivo = S/ 11,500,000
B7: =Datos!B4 -> Efectivo y equivalente de efectivo | C7: - | D7: =Datos!B10 -> Tributos por pagar | E7: =Datos!C10 -> 756000 | G7: Utilidad Bruta | H7: =SUM(H5:H6) -> 2000000 | J7: EFECTIVO requerido = S/ 159,000
B8: =Datos!B7 -> Inventarios de materiales de construcción | C8: =Datos!C7 -> 1600000 | D8: =Datos!B12 -> Obligaciones financieras (CP) | E8: =Datos!C12 -> 1620000 | G8: =Datos!B13 -> Gasto de administración | H8: =-Datos!C13 -> -1300000
B9: =Datos!B6 -> Valorizaciones por cobrar | C9: =Datos!C6 -> 2400000 | D9: =Datos!B20 -> Cuentas por pagar subcontratistas | E9: =Datos!C20 -> 1405000 | G9: =Datos!B19 -> Gastos de comisiones | H9: =-Datos!C19 -> -176000
B10: Total Activo corriente | C10: =SUM(C8:C9) -> 4000000 | D10: Total pasivo corriente | E10: =SUM(E7:E9) -> 3781000 | G10: Utilidad Operativa | H10: =H7+H8+H9 -> 524000
D11: Pasivo No Corriente | G11: =Datos!B8 -> Ingreso por enajenación activo | H11: =Datos!C8 -> 475000
B12: Activo No Corriente | D12: =Datos!B14 -> Obligaciones financieras (LP) | E12: =Datos!C14 -> 4000000 | G12: =Datos!B11 -> Gastos financieros | H12: =-Datos!C11 -> -18000
B13: =Datos!B18 -> Maquinaria y equipo, IME, PPE | C13: =Datos!C18 -> 7500000 | D13: Total pasivo no corriente | E13: =E12 -> 4000000 | G13: =Datos!B21 -> Costo enajenación activo | H13: =-Datos!C21 -> -500000
B14: Total Activo no corriente | C14: =SUM(C13) -> 7500000 | D14: Total pasivo | E14: =E10+E13 -> 7781000 | G14: Utilidad antes Impuestos | H14: =SUM(H10:H13) -> 481000
G15: =Datos!B9 -> Gasto por impuesto a las ganancias | H15: =-Datos!C9 -> -182000
D16: Patrimonio | G16: Utilidad del ejercicio | H16: =SUM(H14:H15) -> 299000
D17: =Datos!B22 -> Capital social | E17: =Datos!C22 -> 2159000
D18: =Datos!B16 -> Reserva legal | E18: =Datos!C16 -> 420000
D19: Resultado acumulado | E19: =H16 -> 299000
D20: =Datos!B17 -> Resultado acumulado al 31.12.2024 | E20: =Datos!C17 -> 1000000
D21: Total patrimonio | E21: =SUM(E17:E20) -> 3878000
B22: Total Activos | C22: =SUM(C14+C10) -> 11500000 | D22: Total Pasivo y Patrimonio | E22: =E14+E21 -> 11659000
B23: Efectivo | C23: =E22-C22 -> 159000
